[
  {
    "listing": "/movies.html",
    "items": []
  },
  {
    "listing": "/projects/index.html",
    "items": []
  },
  {
    "listing": "/movieblog/index.html",
    "items": [
      "/movieblog/fifth-post/index.html",
      "/movieblog/sixth-post/index.html",
      "/movieblog/seventh-post/index.html",
      "/movieblog/eighth-post/index.html",
      "/movieblog/ninth-post/index.html",
      "/movieblog/tenth-post/index.html",
      "/movieblog/eleventh-post/index.html",
      "/movieblog/twelfth-post/index.html",
      "/movieblog/thirteenth-post/Untitled.html",
      "/movieblog/fourteenth-post/index.html",
      "/movieblog/fifteenth-post/index.html",
      "/movieblog/sixteenth-post/index.html",
      "/movieblog/seventeenth-post/index.html",
      "/movieblog/eighteenth-post/index.html",
      "/movieblog/nineteenth-post/index.html",
      "/movieblog/twentieth-post/index.html",
      "/movieblog/twentyfirst-post/index.html",
      "/movieblog/twentythird-post/index.html",
      "/movieblog/twentysecond-post/index.html",
      "/movieblog/twentyfourth-post/index.html",
      "/movieblog/twentyfifth-post/index.html",
      "/movieblog/twentysixth-post/index.html",
      "/movieblog/fourth-post/index.html",
      "/movieblog/third-post/index.html",
      "/movieblog/first-post/index.html",
      "/movieblog/second-post/index.html"
    ]
  },
  {
    "listing": "/movieblog/goodwillhunting/index.html",
    "items": []
  }
]